README
setup.py
iflake8/__init__.py
iflake8.egg-info/PKG-INFO
iflake8.egg-info/SOURCES.txt
iflake8.egg-info/dependency_links.txt
iflake8.egg-info/top_level.txt
tests/__init__.py