Metadata-Version: 1.1
Name: iflake8
Version: 0.0.1
Summary: The ultimate python style checker
Home-page: http://packages.python.org/iflake8
Author: Varun Sharma
Author-email: varunsharmalive@gmail.com
License: MIT
Keywords: django pep8 flake8 isort
Platform: UNKNOWN
Classifier: Development Status :: 3 - Alpha
Classifier: Topic :: Utilities
Classifier: License :: OSI Approved :: MIT License
